terminator_test_cleaner/__init__.py
terminator_test_cleaner-0.1.5.dist-info/METADATA
terminator_test_cleaner-0.1.5.dist-info/WHEEL
terminator_test_cleaner-0.1.5.dist-info/RECORD
