Metadata-Version: 2.4
Name: terminator-test-cleaner
Version: 0.1.5
Summary: A test package for terminator testing
Project-URL: Homepage, https://github.com/example/terminator-test-cleaner
Author-email: Test Author <test@example.com>
Classifier: License :: OSI Approved :: MIT License
Classifier: Operating System :: OS Independent
Classifier: Programming Language :: Python :: 3
Requires-Python: >=3.7
